MANIFEST.in
Products.naked_plone-configure.zcml
README.txt
setup.py
Products/__init__.py
Products.naked_plone.egg-info/PKG-INFO
Products.naked_plone.egg-info/SOURCES.txt
Products.naked_plone.egg-info/dependency_links.txt
Products.naked_plone.egg-info/entry_points.txt
Products.naked_plone.egg-info/namespace_packages.txt
Products.naked_plone.egg-info/not-zip-safe
Products.naked_plone.egg-info/requires.txt
Products.naked_plone.egg-info/top_level.txt
Products/naked_plone/__init__.py
Products/naked_plone/configure.zcml
Products/naked_plone/profiles.zcml
Products/naked_plone/setuphandlers.py
Products/naked_plone/skins.zcml
Products/naked_plone/tests.py
Products/naked_plone/version.txt
Products/naked_plone/browser/__init__.py
Products/naked_plone/browser/configure.zcml
Products/naked_plone/browser/interfaces.py
Products/naked_plone/browser/viewlet.pt
Products/naked_plone/browser/viewlets.py
Products/naked_plone/browser/images/README.txt
Products/naked_plone/browser/stylesheets/README.txt
Products/naked_plone/browser/stylesheets/main.css
Products/naked_plone/profiles/default/Products.naked_plone_various.txt
Products/naked_plone/profiles/default/actions.xml
Products/naked_plone/profiles/default/cssregistry.xml
Products/naked_plone/profiles/default/import_steps.xml
Products/naked_plone/profiles/default/jsregistry.xml
Products/naked_plone/profiles/default/metadata.xml
Products/naked_plone/profiles/default/skins.xml
Products/naked_plone/profiles/default/viewlets.xml
Products/naked_plone/skins/Products_naked_plone_custom_images/CONTENT.txt
Products/naked_plone/skins/Products_naked_plone_custom_images/plone-logo-64.png
Products/naked_plone/skins/Products_naked_plone_custom_templates/CONTENT.txt
Products/naked_plone/skins/Products_naked_plone_styles/CONTENT.txt
Products/naked_plone/skins/Products_naked_plone_styles/base.css.dtml
Products/naked_plone/skins/Products_naked_plone_styles/base_properties.props
Products/naked_plone/skins/Products_naked_plone_styles/portlets.css.dtml
Products/naked_plone/skins/Products_naked_plone_styles/public.css.dtml
docs/HISTORY.txt
docs/INSTALL.txt
docs/LICENSE.GPL
docs/LICENSE.txt
docs/SCREENSHOT.PNG