Metadata-Version: 1.0
Name: Products.naked-plone
Version: 0.1
Summary: An installable theme for Plone 3.0 that does little but override default public stylesheets with empty ones.
Home-page: https://svn.plone.org/svn/collective/Products.naked_plone/
Author: Alex Clark
Author-email: aclark@aclark.net
License: GPL
Keywords: web zope plone theme
Platform: UNKNOWN
Classifier: Framework :: Plone
Classifier: Programming Language :: Python
Classifier: Topic :: Software Development :: Libraries :: Python Modules
